{
  "images": {
    "happyMole": "https://i.imgur.com/tejeMhR.png",
    "angryMole": "https://i.imgur.com/Upj2Blp.png",
    "backgroundImage": "https://i.imgur.com/2MxAkFs.png"
  },
  "@@editor": [
    {
      "key": "images",
      "name": "Images",
      "icon": "🖼️",
      "source": "images.json",
      "fields": [
        {
          "key": "happyMole",
          "name": "Happy Mole Image",
          "description": "Image for happy mole",
          "type": "image"
        },
        {
          "key": "angryMole",
          "name": "Angry Mole Image",
          "description": "Image for angry mole",
          "type": "image"
        },
        {
          "key": "backgroundImage",
          "name": "Background Image",
          "description": "Background image",
          "type": "image"
        }
      ]
    }
  ]
}